odoo10_addon_hotel_housekeeping-10.0.1.0.0.99.dev15-nspkg.pth
odoo/addons/hotel_housekeeping/README.rst
odoo/addons/hotel_housekeeping/__init__.py
odoo/addons/hotel_housekeeping/__manifest__.py
odoo/addons/hotel_housekeeping/LICENSE/LICENSE
odoo/addons/hotel_housekeeping/i18n/es.po
odoo/addons/hotel_housekeeping/i18n/fr_BE.po
odoo/addons/hotel_housekeeping/i18n/sv.po
odoo/addons/hotel_housekeeping/models/__init__.py
odoo/addons/hotel_housekeeping/models/hotel_housekeeping.py
odoo/addons/hotel_housekeeping/report/__init__.py
odoo/addons/hotel_housekeeping/report/hotel_housekeeping_report.xml
odoo/addons/hotel_housekeeping/report/housekeeping_report.py
odoo/addons/hotel_housekeeping/security/ir.model.access.csv
odoo/addons/hotel_housekeeping/static/description/HHK1.png
odoo/addons/hotel_housekeeping/static/description/HHK2.png
odoo/addons/hotel_housekeeping/static/description/HHK3.png
odoo/addons/hotel_housekeeping/static/description/HHK4.png
odoo/addons/hotel_housekeeping/static/description/icon.png
odoo/addons/hotel_housekeeping/static/description/serpent.png
odoo/addons/hotel_housekeeping/tests/__init__.py
odoo/addons/hotel_housekeeping/tests/test_hotel_housekeeping.py
odoo/addons/hotel_housekeeping/views/activity_detail.xml
odoo/addons/hotel_housekeeping/views/hotel_housekeeping_data.xml
odoo/addons/hotel_housekeeping/views/hotel_housekeeping_view.xml
odoo/addons/hotel_housekeeping/wizard/__init__.py
odoo/addons/hotel_housekeeping/wizard/hotel_housekeeping_wizard.xml
odoo/addons/hotel_housekeeping/wizard/housekeeping_wizard.py
odoo10_addon_hotel_housekeeping-10.0.1.0.0.99.dev15.dist-info/METADATA
odoo10_addon_hotel_housekeeping-10.0.1.0.0.99.dev15.dist-info/WHEEL
odoo10_addon_hotel_housekeeping-10.0.1.0.0.99.dev15.dist-info/namespace_packages.txt
odoo10_addon_hotel_housekeeping-10.0.1.0.0.99.dev15.dist-info/top_level.txt
odoo10_addon_hotel_housekeeping-10.0.1.0.0.99.dev15.dist-info/RECORD
